Metadata-Version: 2.1
Name: peerannot
Version: 0.0.1.post41
Summary: Crowdsourcing library
Download-URL: https://github.com/peerannot/peerannot.git
Maintainer: Tanguy Lefort
Maintainer-email: tanguy.lefort@umontpellier.fr
License: BSD (3-clause)
Platform: any
Classifier: Development Status :: 4 - Beta
Classifier: Environment :: Console
Classifier: Intended Audience :: Developers
Classifier: Intended Audience :: Science/Research
Classifier: License :: OSI Approved :: BSD License
Classifier: Operating System :: OS Independent
Classifier: Programming Language :: Python :: 3.8
Classifier: Programming Language :: Python :: 3.9
Classifier: Topic :: Scientific/Engineering
Classifier: Topic :: Utilities
Classifier: Topic :: Software Development :: Libraries
Requires-Python: >=3.8
License-File: LICENSE
Requires-Dist: numpy
Requires-Dist: scipy
Requires-Dist: pandas
Requires-Dist: click >=8.0
Requires-Dist: torch
Requires-Dist: torchvision
Requires-Dist: torchmetrics
Requires-Dist: scikit-learn
Requires-Dist: plotly >=4.12
Requires-Dist: tqdm
Requires-Dist: pooch
Requires-Dist: Pillow
Provides-Extra: test
Requires-Dist: pytest ; extra == 'test'
Requires-Dist: pytest-cov ; extra == 'test'
Requires-Dist: pytest-timeout ; extra == 'test'
Requires-Dist: coverage ; extra == 'test'
